{
  "version": 6,
  "cmakeMinimumRequired": {
    "major": 3,
    "minor": 28,
    "patch": 0
  },
  "configurePresets": [
    {
      "name": "ninja-debug",
      "displayName": "Ninja Debug",
      "generator": "Ninja",
      "binaryDir": "${sourceDir}/build/debug",
      "cacheVariables": {
        "CMAKE_BUILD_TYPE": "Debug"
      }
    },
    {
      "name": "ninja-release",
      "displayName": "Ninja Release",
      "generator": "Ninja",
      "binaryDir": "${sourceDir}/build/release",
      "cacheVariables": {
        "CMAKE_BUILD_TYPE": "Release"
      }
    }
  ],
  "buildPresets": [
    {
      "name": "build-debug",
      "configurePreset": "ninja-debug"
    },
    {
      "name": "build-release",
      "configurePreset": "ninja-release"
    }
  ],
  "testPresets": [
    {
      "name": "test-debug",
      "configurePreset": "ninja-debug",
      "output": {
        "outputOnFailure": true
      }
    }
  ]
}
